wobblywalrus/__init__.py
wobblywalrus/cache_manager.py
wobblywalrus/cli.py
wobblywalrus/config.py
wobblywalrus/get_place_id.py
wobblywalrus/place_service.py
wobblywalrus/search_cache.py
wobblywalrus/utils.py
wobblywalrus/yaml_to_place_id.py
wobblywalrus/search/__init__.py
wobblywalrus/search/search.py
wobblywalrus/search/strategies.py
wobblywalrus-0.1.1.dist-info/METADATA
wobblywalrus-0.1.1.dist-info/WHEEL
wobblywalrus-0.1.1.dist-info/entry_points.txt
wobblywalrus-0.1.1.dist-info/RECORD
