Metadata-Version: 2.4
Name: wobblywalrus
Version: 0.1.1
Summary: Add your description here
Author-email: Taylor Monacelli <taylormonacelli@gmail.com>
Requires-Python: >=3.12
Requires-Dist: googlemaps>=4.10.0
Requires-Dist: platformdirs>=4.3.6
Requires-Dist: python-dotenv>=1.0.0
Requires-Dist: pyyaml>=6.0.2
